README.md
setup.py
pyompa/__init__.py
pyompa/endmemberpenaltyfunc.py
pyompa/ompacore.py
pyompa/parse_config.py
pyompa/plotting.py
pyompa/split_thermocline.py
pyompa/thermocline_array.py
pyompa/util.py
pyompa.egg-info/PKG-INFO
pyompa.egg-info/SOURCES.txt
pyompa.egg-info/dependency_links.txt
pyompa.egg-info/requires.txt
pyompa.egg-info/top_level.txt
scripts/run_ompa_given_config