Metadata-Version: 2.1
Name: pyompa
Version: 0.4.2.1
Summary: Python OMPA
Home-page: https://github.com/nitrogenlab/pyompa
Author: Avanti Shrikumar
Author-email: avanti.shrikumar@gmail.com
Provides-Extra: altair
